{
    "e4": {
        "c5": {
            "Nf3": {
                "Nc6": {
                    "Bc4": {
                        "e6": {}
                    }
                }
            }
        }
    },
    "h3": {
        "c5": {}
    },
    "Nf3": {
        "c5": {
            "d4": {
                "cxd4": {
                    "Nxc4": {
                        "d5": {}
                    }
                }
            }
        }
    },
    "g3": {
        "c5": {
            "Bg2": {
                "d5": {
                    "h4": {
                        "Nc6": {}
                    },
                    "e3": {
                        "Nc6": {}
                    }
                }
            }
        }
    },
    "f4": {
        "c5": {
            "d4": {
                "cxd4": {}
            },
            "Nf3": {
                "Nc6": {
                    "Nc3": {
                        "d5": {}
                    }
                }
            }
        }
    },
    "e3": {
        "c5": {
            "d4": {
                "cxd4": {
                    "exd4": {
                        "d5": {
                            "Bd3": {
                                "Nc6": {
                                    "Nf3": {
                                        "Bg4": {}
                                    }
                                }
                            }
                        }
                    },
                    "Qxd4": {
                        "Nc6": {
                            "Qd1": {
                                "g6": {
                                    "c3": {
                                        "Bg7": {
                                            "h4": {
                                                "Nf6": {
                                                    "Nf3": {
                                                        "O-O": {}
                                                    }
                                                }
                                            }
                                        }
                                    }
                                }
                            }
                        }
                    }
                }
            },
            "c3": {
                "d5": {}
            }
        }
    }
}